cassandracrud/__init__.py
cassandracrud/core.py
cassandracrud-0.1.0.dist-info/LICENSE
cassandracrud-0.1.0.dist-info/METADATA
cassandracrud-0.1.0.dist-info/WHEEL
cassandracrud-0.1.0.dist-info/top_level.txt
cassandracrud-0.1.0.dist-info/RECORD
