Metadata-Version: 2.1
Name: cassandracrud
Version: 0.1.0
Summary: A simple CRUD library for Apache Cassandra
Home-page: https://github.com/cervantes79/cassandracrud
Author: Baris Genc
Author-email: info@gencbaris.com
Classifier: Development Status :: 3 - Alpha
Classifier: Intended Audience :: Developers
Classifier: License :: OSI Approved :: MIT License
Classifier: Programming Language :: Python :: 3
Classifier: Programming Language :: Python :: 3.7
Classifier: Programming Language :: Python :: 3.8
Classifier: Programming Language :: Python :: 3.9
Requires-Python: >=3.7
License-File: LICENSE
Requires-Dist: cassandra-driver>=3.29.1
Requires-Dist: pandas>=1.0.0
